[
    {
        "2019": "4",
        "id": "1",
        "Id-ranking": "10",
        "Institucion": "Ministerio de Comunicaciones, Infraestructura y Vivienda",
        "Organismo": "Organismo Ejecutivo",
        "id-institucion": "CIV",
        "Recolección y producción de datos": "4",
        "Disponibilidad en linea": "3",
        "Plataformas": "4",
        "Acceso": "4",
        "Periodicidad de actualización": "3",
        "Licencia": "7",
        "Formatos": "1",
        "Legibilidad": "1",
        "Gobernanza": "1",
        "IndicadorInstitucion2021": "4",
        "Recolección COVID-19": "1",
        "Disponibilidad  COVID-19": "1",
        "Plataformas  COVID-19": "1",
        "Respuesta COVID-19": "1",
        "Indicador 2021": "4",
        "Tendencia": "Igual"
    },
    {
        "2019": "6",
        "id": "2",
        "Id-ranking": "6",
        "Institucion": "Ministerio de Agricultura, Ganadería y Alimentación",
        "Organismo": "Organismo Ejecutivo",
        "id-institucion": "MAGA",
        "Recolección y producción de datos": "4",
        "Disponibilidad en linea": "3",
        "Plataformas": "3",
        "Acceso": "3",
        "Periodicidad de actualización": "3",
        "Licencia": "4",
        "Formatos": "4",
        "Legibilidad": "4",
        "Gobernanza": "8",
        "IndicadorInstitucion2021": "4",
        "Recolección COVID-19": "4",
        "Disponibilidad  COVID-19": "3",
        "Plataformas  COVID-19": "1",
        "Respuesta COVID-19": "3",
        "Indicador 2021": "4",
        "Tendencia": "Bajo"
    },
    {
        "2019": "2",
        "id": "3",
        "Id-ranking": "4",
        "Institucion": "Ministerio de Ambiente y Recursos Naturales",
        "Organismo": "Organismo Ejecutivo",
        "id-institucion": "MARN",
        "Recolección y producción de datos": "3",
        "Disponibilidad en linea": "4",
        "Plataformas": "2",
        "Acceso": "3",
        "Periodicidad de actualización": "4",
        "Licencia": "7",
        "Formatos": "1",
        "Legibilidad": "1",
        "Gobernanza": "8",
        "IndicadorInstitucion2021": "4",
        "Recolección COVID-19": "1",
        "Disponibilidad  COVID-19": "2",
        "Plataformas  COVID-19": "1",
        "Respuesta COVID-19": "1",
        "Indicador 2021": "4",
        "Tendencia": "Subio"
    },
    {
        "2019": "2",
        "id": "4",
        "Id-ranking": "3",
        "Institucion": "Ministerio de Cultura y Deportes",
        "Organismo": "Organismo Ejecutivo",
        "id-institucion": "MCD",
        "Recolección y producción de datos": "5",
        "Disponibilidad en linea": "3",
        "Plataformas": "3",
        "Acceso": "4",
        "Periodicidad de actualización": "4",
        "Licencia": "7",
        "Formatos": "1",
        "Legibilidad": "1",
        "Gobernanza": "5",
        "IndicadorInstitucion2021": "4",
        "Recolección COVID-19": "3",
        "Disponibilidad  COVID-19": "3",
        "Plataformas  COVID-19": "2",
        "Respuesta COVID-19": "2",
        "Indicador 2021": "4",
        "Tendencia": "Subio"
    },
    {
        "2019": "3",
        "id": "5",
        "Id-ranking": "2",
        "Institucion": "Ministerio de Energía y Minas",
        "Organismo": "Organismo Ejecutivo",
        "id-institucion": "MEM",
        "Recolección y producción de datos": "3",
        "Disponibilidad en linea": "3",
        "Plataformas": "3",
        "Acceso": "4",
        "Periodicidad de actualización": "3",
        "Licencia": "7",
        "Formatos": "1",
        "Legibilidad": "1",
        "Gobernanza": "8",
        "IndicadorInstitucion2021": "4",
        "Recolección COVID-19": "1",
        "Disponibilidad  COVID-19": "1",
        "Plataformas  COVID-19": "1",
        "Respuesta COVID-19": "1",
        "Indicador 2021": "4",
        "Tendencia": "Subio"
    },
    {
        "2019": "1",
        "id": "6",
        "Id-ranking": "14",
        "Institucion": "Ministerio de Desarrollo Social",
        "Organismo": "Organismo Ejecutivo",
        "id-institucion": "MIDES",
        "Recolección y producción de datos": "3",
        "Disponibilidad en linea": "3",
        "Plataformas": "4",
        "Acceso": "3",
        "Periodicidad de actualización": "4",
        "Licencia": "4",
        "Formatos": "4",
        "Legibilidad": "4",
        "Gobernanza": "1",
        "IndicadorInstitucion2021": "3",
        "Recolección COVID-19": "4",
        "Disponibilidad  COVID-19": "4",
        "Plataformas  COVID-19": "1",
        "Respuesta COVID-19": "3",
        "Indicador 2021": "3",
        "Tendencia": "Subio"
    },
    {
        "2019": "0",
        "id": "7",
        "Id-ranking": "21",
        "Institucion": "Ministerio de la Defensa Nacional",
        "Organismo": "Organismo Ejecutivo",
        "id-institucion": "MINDEF",
        "Recolección y producción de datos": "3",
        "Disponibilidad en linea": "3",
        "Plataformas": "4",
        "Acceso": "3",
        "Periodicidad de actualización": "3",
        "Licencia": "4",
        "Formatos": "1",
        "Legibilidad": "1",
        "Gobernanza": "1",
        "IndicadorInstitucion2021": "3",
        "Recolección COVID-19": "2",
        "Disponibilidad  COVID-19": "1",
        "Plataformas  COVID-19": "1",
        "Respuesta COVID-19": "1",
        "Indicador 2021": "3",
        "Tendencia": "Subio"
    },
    {
        "2019": "3",
        "id": "8",
        "Id-ranking": "5",
        "Institucion": "Ministerio de Economía",
        "Organismo": "Organismo Ejecutivo",
        "id-institucion": "MINECO",
        "Recolección y producción de datos": "3",
        "Disponibilidad en linea": "2",
        "Plataformas": "2",
        "Acceso": "4",
        "Periodicidad de actualización": "3",
        "Licencia": "7",
        "Formatos": "1",
        "Legibilidad": "1",
        "Gobernanza": "6",
        "IndicadorInstitucion2021": "4",
        "Recolección COVID-19": "1",
        "Disponibilidad  COVID-19": "1",
        "Plataformas  COVID-19": "1",
        "Respuesta COVID-19": "1",
        "Indicador 2021": "4",
        "Tendencia": "Subio"
    },
    {
        "2019": "7",
        "id": "9",
        "Id-ranking": "9",
        "Institucion": "Ministerio de Educación",
        "Organismo": "Organismo Ejecutivo",
        "id-institucion": "MINEDUC",
        "Recolección y producción de datos": "4",
        "Disponibilidad en linea": "2",
        "Plataformas": "7",
        "Acceso": "3",
        "Periodicidad de actualización": "4",
        "Licencia": "5",
        "Formatos": "3",
        "Legibilidad": "3",
        "Gobernanza": "2",
        "IndicadorInstitucion2021": "4",
        "Recolección COVID-19": "2",
        "Disponibilidad  COVID-19": "3",
        "Plataformas  COVID-19": "1",
        "Respuesta COVID-19": "2",
        "Indicador 2021": "4",
        "Tendencia": "Bajo"
    },
    {
        "2019": "5",
        "id": "10",
        "Id-ranking": "11",
        "Institucion": "Ministerio de Relaciones Exteriores",
        "Organismo": "Organismo Ejecutivo",
        "id-institucion": "MINEX",
        "Recolección y producción de datos": "3",
        "Disponibilidad en linea": "3",
        "Plataformas": "2",
        "Acceso": "3",
        "Periodicidad de actualización": "3",
        "Licencia": "2",
        "Formatos": "4",
        "Legibilidad": "3",
        "Gobernanza": "8",
        "IndicadorInstitucion2021": "4",
        "Recolección COVID-19": "2",
        "Disponibilidad  COVID-19": "3",
        "Plataformas  COVID-19": "1",
        "Respuesta COVID-19": "3",
        "Indicador 2021": "4",
        "Tendencia": "Bajo"
    },
    {
        "2019": "8",
        "id": "11",
        "Id-ranking": "1",
        "Institucion": "Ministerio de Finanzas Públicas",
        "Organismo": "Organismo Ejecutivo",
        "id-institucion": "MINFIN",
        "Recolección y producción de datos": "7",
        "Disponibilidad en linea": "7",
        "Plataformas": "8",
        "Acceso": "7",
        "Periodicidad de actualización": "8",
        "Licencia": "7",
        "Formatos": "7",
        "Legibilidad": "7",
        "Gobernanza": "8",
        "IndicadorInstitucion2021": "7",
        "Recolección COVID-19": "5",
        "Disponibilidad  COVID-19": "5",
        "Plataformas  COVID-19": "2",
        "Respuesta COVID-19": "5",
        "Indicador 2021": "7",
        "Tendencia": "Bajo"
    },
    {
        "2019": "4",
        "id": "12",
        "Id-ranking": "15",
        "Institucion": "Ministerio de Gobernación",
        "Organismo": "Organismo Ejecutivo",
        "id-institucion": "MINGOB",
        "Recolección y producción de datos": "2",
        "Disponibilidad en linea": "3",
        "Plataformas": "2",
        "Acceso": "3",
        "Periodicidad de actualización": "3",
        "Licencia": "3",
        "Formatos": "1",
        "Legibilidad": "1",
        "Gobernanza": "5",
        "IndicadorInstitucion2021": "3",
        "Recolección COVID-19": "1",
        "Disponibilidad  COVID-19": "1",
        "Plataformas  COVID-19": "1",
        "Respuesta COVID-19": "1",
        "Indicador 2021": "3",
        "Tendencia": "Bajo"
    },
    {
        "2019": "4",
        "id": "13",
        "Id-ranking": "13",
        "Institucion": "Ministerio de Trabajo y Previsión Social",
        "Organismo": "Organismo Ejecutivo",
        "id-institucion": "MINTRAB",
        "Recolección y producción de datos": "2",
        "Disponibilidad en linea": "2",
        "Plataformas": "3",
        "Acceso": "4",
        "Periodicidad de actualización": "3",
        "Licencia": "4",
        "Formatos": "1",
        "Legibilidad": "1",
        "Gobernanza": "8",
        "IndicadorInstitucion2021": "3",
        "Recolección COVID-19": "3",
        "Disponibilidad  COVID-19": "3",
        "Plataformas  COVID-19": "2",
        "Respuesta COVID-19": "2",
        "Indicador 2021": "3",
        "Tendencia": "Bajo"
    },
    {
        "2019": "6",
        "id": "14",
        "Id-ranking": "7",
        "Institucion": "Ministerio de Salud Pública y Asistencia Social",
        "Organismo": "Organismo Ejecutivo",
        "id-institucion": "MSPAS",
        "Recolección y producción de datos": "5",
        "Disponibilidad en linea": "4",
        "Plataformas": "6",
        "Acceso": "3",
        "Periodicidad de actualización": "4",
        "Licencia": "4",
        "Formatos": "2",
        "Legibilidad": "3",
        "Gobernanza": "4",
        "IndicadorInstitucion2021": "4",
        "Recolección COVID-19": "5",
        "Disponibilidad  COVID-19": "4",
        "Plataformas  COVID-19": "3",
        "Respuesta COVID-19": "3",
        "Indicador 2021": "4",
        "Tendencia": "Bajo"
    },
    {
        "2019": "0",
        "id": "15",
        "Id-ranking": "30",
        "Institucion": "Secretaría de Asuntos Agrarios de la Presidencia de la República",
        "Organismo": "Organismo Ejecutivo",
        "id-institucion": "SAA",
        "Recolección y producción de datos": "0",
        "Disponibilidad en linea": "0",
        "Plataformas": "0",
        "Acceso": "0",
        "Periodicidad de actualización": "0",
        "Licencia": "0",
        "Formatos": "0",
        "Legibilidad": "0",
        "Gobernanza": "0",
        "IndicadorInstitucion2021": "0",
        "Recolección COVID-19": "0",
        "Disponibilidad  COVID-19": "0",
        "Plataformas  COVID-19": "0",
        "Respuesta COVID-19": "0",
        "Indicador 2021": "0",
        "Tendencia": "N/D"
    },
    {
        "2019": "4",
        "id": "16",
        "Id-ranking": "28",
        "Institucion": "Secretaría de Asuntos Administrativos y de Seguridad de la Presidencia de la República",
        "Organismo": "Organismo Ejecutivo",
        "id-institucion": "SAAS",
        "Recolección y producción de datos": "3",
        "Disponibilidad en linea": "2",
        "Plataformas": "2",
        "Acceso": "2",
        "Periodicidad de actualización": "3",
        "Licencia": "2",
        "Formatos": "1",
        "Legibilidad": "4",
        "Gobernanza": "1",
        "IndicadorInstitucion2021": "2",
        "Recolección COVID-19": "2",
        "Disponibilidad  COVID-19": "2",
        "Plataformas  COVID-19": "1",
        "Respuesta COVID-19": "2",
        "Indicador 2021": "2",
        "Tendencia": "Bajo"
    },
    {
        "2019": "3",
        "id": "17",
        "Id-ranking": "12",
        "Institucion": "Secretaría de Bienestar Social de la Presidencia",
        "Organismo": "Organismo Ejecutivo",
        "id-institucion": "SBS",
        "Recolección y producción de datos": "3",
        "Disponibilidad en linea": "3",
        "Plataformas": "2",
        "Acceso": "5",
        "Periodicidad de actualización": "3",
        "Licencia": "4",
        "Formatos": "1",
        "Legibilidad": "1",
        "Gobernanza": "8",
        "IndicadorInstitucion2021": "4",
        "Recolección COVID-19": "1",
        "Disponibilidad  COVID-19": "1",
        "Plataformas  COVID-19": "1",
        "Respuesta COVID-19": "1",
        "Indicador 2021": "4",
        "Tendencia": "Subio"
    },
    {
        "2019": "3",
        "id": "18",
        "Id-ranking": "16",
        "Institucion": "Secretaría de Coordinación Ejecutiva de la Presidencia",
        "Organismo": "Organismo Ejecutivo",
        "id-institucion": "SCEP",
        "Recolección y producción de datos": "3",
        "Disponibilidad en linea": "3",
        "Plataformas": "2",
        "Acceso": "5",
        "Periodicidad de actualización": "3",
        "Licencia": "8",
        "Formatos": "1",
        "Legibilidad": "1",
        "Gobernanza": "1",
        "IndicadorInstitucion2021": "3",
        "Recolección COVID-19": "1",
        "Disponibilidad  COVID-19": "1",
        "Plataformas  COVID-19": "1",
        "Respuesta COVID-19": "1",
        "Indicador 2021": "3",
        "Tendencia": "Igual"
    },
    {
        "2019": "3",
        "id": "19",
        "Id-ranking": "26",
        "Institucion": "Secretaría de Comunicación Social de la Presidencia",
        "Organismo": "Organismo Ejecutivo",
        "id-institucion": "SCSPR",
        "Recolección y producción de datos": "2",
        "Disponibilidad en linea": "3",
        "Plataformas": "2",
        "Acceso": "3",
        "Periodicidad de actualización": "3",
        "Licencia": "4",
        "Formatos": "1",
        "Legibilidad": "1",
        "Gobernanza": "1",
        "IndicadorInstitucion2021": "2",
        "Recolección COVID-19": "2",
        "Disponibilidad  COVID-19": "2",
        "Plataformas  COVID-19": "1",
        "Respuesta COVID-19": "1",
        "Indicador 2021": "2",
        "Tendencia": "Bajo"
    },
    {
        "2019": "4",
        "id": "20",
        "Id-ranking": "19",
        "Institucion": "Secretaría de Planificación y Programación de la Presidencia",
        "Organismo": "Organismo Ejecutivo",
        "id-institucion": "SEGEPLAN",
        "Recolección y producción de datos": "3",
        "Disponibilidad en linea": "3",
        "Plataformas": "6",
        "Acceso": "3",
        "Periodicidad de actualización": "3",
        "Licencia": "3",
        "Formatos": "3",
        "Legibilidad": "2",
        "Gobernanza": "1",
        "IndicadorInstitucion2021": "3",
        "Recolección COVID-19": "3",
        "Disponibilidad  COVID-19": "3",
        "Plataformas  COVID-19": "1",
        "Respuesta COVID-19": "2",
        "Indicador 2021": "3",
        "Tendencia": "Bajo"
    },
    {
        "2019": "3",
        "id": "21",
        "Id-ranking": "25",
        "Institucion": "Secretaría Nacional de Administración de Bienes en Extinción",
        "Organismo": "Organismo Ejecutivo",
        "id-institucion": "SENABED",
        "Recolección y producción de datos": "3",
        "Disponibilidad en linea": "3",
        "Plataformas": "3",
        "Acceso": "3",
        "Periodicidad de actualización": "3",
        "Licencia": "2",
        "Formatos": "1",
        "Legibilidad": "1",
        "Gobernanza": "2",
        "IndicadorInstitucion2021": "3",
        "Recolección COVID-19": "1",
        "Disponibilidad  COVID-19": "1",
        "Plataformas  COVID-19": "1",
        "Respuesta COVID-19": "1",
        "Indicador 2021": "3",
        "Tendencia": "Igual"
    },
    {
        "2019": "6",
        "id": "22",
        "Id-ranking": "24",
        "Institucion": "Secretaría Nacional de Ciencia y Tecnología",
        "Organismo": "Organismo Ejecutivo",
        "id-institucion": "SENACYT",
        "Recolección y producción de datos": "3",
        "Disponibilidad en linea": "3",
        "Plataformas": "3",
        "Acceso": "3",
        "Periodicidad de actualización": "3",
        "Licencia": "3",
        "Formatos": "1",
        "Legibilidad": "1",
        "Gobernanza": "1",
        "IndicadorInstitucion2021": "3",
        "Recolección COVID-19": "1",
        "Disponibilidad  COVID-19": "1",
        "Plataformas  COVID-19": "1",
        "Respuesta COVID-19": "1",
        "Indicador 2021": "3",
        "Tendencia": "Bajo"
    },
    {
        "2019": "0",
        "id": "23",
        "Id-ranking": "29",
        "Institucion": "Secretaría de la Paz de la Presidencia de la República",
        "Organismo": "Organismo Ejecutivo",
        "id-institucion": "SEPAZ",
        "Recolección y producción de datos": "0",
        "Disponibilidad en linea": "0",
        "Plataformas": "0",
        "Acceso": "0",
        "Periodicidad de actualización": "0",
        "Licencia": "0",
        "Formatos": "0",
        "Legibilidad": "0",
        "Gobernanza": "0",
        "IndicadorInstitucion2021": "0",
        "Recolección COVID-19": "0",
        "Disponibilidad  COVID-19": "0",
        "Plataformas  COVID-19": "0",
        "Respuesta COVID-19": "0",
        "Indicador 2021": "0",
        "Tendencia": "N/D"
    },
    {
        "2019": "4",
        "id": "24",
        "Id-ranking": "8",
        "Institucion": "Secretaría Presidencial de la Mujer",
        "Organismo": "Organismo Ejecutivo",
        "id-institucion": "SEPREM",
        "Recolección y producción de datos": "5",
        "Disponibilidad en linea": "3",
        "Plataformas": "3",
        "Acceso": "3",
        "Periodicidad de actualización": "3",
        "Licencia": "6",
        "Formatos": "3",
        "Legibilidad": "2",
        "Gobernanza": "8",
        "IndicadorInstitucion2021": "4",
        "Recolección COVID-19": "5",
        "Disponibilidad  COVID-19": "4",
        "Plataformas  COVID-19": "3",
        "Respuesta COVID-19": "3",
        "Indicador 2021": "4",
        "Tendencia": "Igual"
    },
    {
        "2019": "6",
        "id": "25",
        "Id-ranking": "18",
        "Institucion": "Secretaría de Seguridad Alimentaria y Nutricional",
        "Organismo": "Organismo Ejecutivo",
        "id-institucion": "SESAN",
        "Recolección y producción de datos": "4",
        "Disponibilidad en linea": "3",
        "Plataformas": "3",
        "Acceso": "5",
        "Periodicidad de actualización": "3",
        "Licencia": "4",
        "Formatos": "1",
        "Legibilidad": "1",
        "Gobernanza": "1",
        "IndicadorInstitucion2021": "3",
        "Recolección COVID-19": "1",
        "Disponibilidad  COVID-19": "1",
        "Plataformas  COVID-19": "1",
        "Respuesta COVID-19": "1",
        "Indicador 2021": "3",
        "Tendencia": "Bajo"
    },
    {
        "2019": "1",
        "id": "26",
        "Id-ranking": "22",
        "Institucion": "Secretaría General de la Presidencia",
        "Organismo": "Organismo Ejecutivo",
        "id-institucion": "SGP",
        "Recolección y producción de datos": "3",
        "Disponibilidad en linea": "3",
        "Plataformas": "2",
        "Acceso": "3",
        "Periodicidad de actualización": "2",
        "Licencia": "6",
        "Formatos": "2",
        "Legibilidad": "3",
        "Gobernanza": "1",
        "IndicadorInstitucion2021": "3",
        "Recolección COVID-19": "4",
        "Disponibilidad  COVID-19": "3",
        "Plataformas  COVID-19": "1",
        "Respuesta COVID-19": "3",
        "Indicador 2021": "3",
        "Tendencia": "Subio"
    },
    {
        "2019": "3",
        "id": "27",
        "Id-ranking": "23",
        "Institucion": "Secretaría de Inteligencia Estratégica del Estado",
        "Organismo": "Organismo Ejecutivo",
        "id-institucion": "SIE",
        "Recolección y producción de datos": "3",
        "Disponibilidad en linea": "3",
        "Plataformas": "2",
        "Acceso": "3",
        "Periodicidad de actualización": "3",
        "Licencia": "3",
        "Formatos": "2",
        "Legibilidad": "2",
        "Gobernanza": "1",
        "IndicadorInstitucion2021": "3",
        "Recolección COVID-19": "3",
        "Disponibilidad  COVID-19": "3",
        "Plataformas  COVID-19": "2",
        "Respuesta COVID-19": "2",
        "Indicador 2021": "3",
        "Tendencia": "Igual"
    },
    {
        "2019": "6",
        "id": "28",
        "Id-ranking": "27",
        "Institucion": "Secretaría de Obras Sociales de la Esposa del Presidente de la República",
        "Organismo": "Organismo Ejecutivo",
        "id-institucion": "SOSEP",
        "Recolección y producción de datos": "2",
        "Disponibilidad en linea": "2",
        "Plataformas": "2",
        "Acceso": "3",
        "Periodicidad de actualización": "3",
        "Licencia": "4",
        "Formatos": "1",
        "Legibilidad": "1",
        "Gobernanza": "1",
        "IndicadorInstitucion2021": "2",
        "Recolección COVID-19": "1",
        "Disponibilidad  COVID-19": "1",
        "Plataformas  COVID-19": "1",
        "Respuesta COVID-19": "1",
        "Indicador 2021": "2",
        "Tendencia": "Bajo"
    },
    {
        "2019": "3",
        "id": "29",
        "Id-ranking": "20",
        "Institucion": "Secretaría Privada de la Presidencia",
        "Organismo": "Organismo Ejecutivo",
        "id-institucion": "SPP",
        "Recolección y producción de datos": "3",
        "Disponibilidad en linea": "3",
        "Plataformas": "2",
        "Acceso": "4",
        "Periodicidad de actualización": "3",
        "Licencia": "4",
        "Formatos": "3",
        "Legibilidad": "3",
        "Gobernanza": "1",
        "IndicadorInstitucion2021": "3",
        "Recolección COVID-19": "3",
        "Disponibilidad  COVID-19": "3",
        "Plataformas  COVID-19": "2",
        "Respuesta COVID-19": "3",
        "Indicador 2021": "3",
        "Tendencia": "Igual"
    },
    {
        "2019": "5",
        "id": "30",
        "Id-ranking": "17",
        "Institucion": "Secretaría contra la Violencia sexual Explotación y Trata de Personas",
        "Organismo": "Organismo Ejecutivo",
        "id-institucion": "SVET",
        "Recolección y producción de datos": "4",
        "Disponibilidad en linea": "3",
        "Plataformas": "3",
        "Acceso": "4",
        "Periodicidad de actualización": "3",
        "Licencia": "3",
        "Formatos": "3",
        "Legibilidad": "3",
        "Gobernanza": "1",
        "IndicadorInstitucion2021": "3",
        "Recolección COVID-19": "3",
        "Disponibilidad  COVID-19": "3",
        "Plataformas  COVID-19": "1",
        "Respuesta COVID-19": "3",
        "Indicador 2021": "3",
        "Tendencia": "Bajo"
    }
]
